dave_core/__init__.py
dave_core/archiv_io.py
dave_core/create.py
dave_core/dave_structure.py
dave_core/model_utils.py
dave_core/progressbar.py
dave_core/settings.py
dave_core/toolbox.py
dave_core/components/__init__.py
dave_core/components/gas_components.py
dave_core/components/loads.py
dave_core/components/power_plants.py
dave_core/components/substations.py
dave_core/components/transformers.py
dave_core/converter/__init__.py
dave_core/converter/converter.py
dave_core/converter/create_gaslib.py
dave_core/converter/create_mynts.py
dave_core/converter/create_pandapipes.py
dave_core/converter/create_pandapower.py
dave_core/converter/elements.py
dave_core/converter/extend_panda.py
dave_core/converter/read_gaslib.py
dave_core/converter/read_simone.py
dave_core/converter/gaslib/CompressorStations.xsd
dave_core/converter/gaslib/GasLib-582-v2.cs
dave_core/datapool/__init__.py
dave_core/datapool/oep_request.py
dave_core/datapool/osm_request.py
dave_core/datapool/read_data.py
dave_core/datapool/data/federalstatesger.h5
dave_core/datapool/data/federalstatesger_meta.xlsx
dave_core/datapool/data/household_power_consumption.h5
dave_core/datapool/data/household_power_consumption_meta.xlsx
dave_core/datapool/data/nuts_regions_meta.xlsx
dave_core/datapool/data/osm_meta.xlsx
dave_core/datapool/data/postalcodesger.h5
dave_core/datapool/data/postalcodesger_meta.xlsx
dave_core/datapool/data/scigridgas_iggielgn_meta.xlsx
dave_core/datapool/data/gaslib/CombinedDecisions.xsd
dave_core/datapool/data/gaslib/Framework.xsd
dave_core/datapool/data/gaslib/Gas.xsd
dave_core/datapool/data/gaslib/GasLib-582-v2.net
dave_core/datapool/data/gaslib/PhysicalValues.xsd
dave_core/datapool/data/gaslib/Scenario.xsd
dave_core/datapool/data/gaslib/Topology.xsd
dave_core/datapool/data/gaslib/inputData.xsd
dave_core/geography/__init__.py
dave_core/geography/geo_utils.py
dave_core/geography/osm_data.py
dave_core/geography/target_area.py
dave_core/io/__init__.py
dave_core/io/convert_format.py
dave_core-1.3.3.dist-info/licenses/AUTHORS.rst
dave_core-1.3.3.dist-info/licenses/LICENSE
dave_core-1.3.3.dist-info/METADATA
dave_core-1.3.3.dist-info/WHEEL
dave_core-1.3.3.dist-info/top_level.txt
dave_core-1.3.3.dist-info/RECORD
