Metadata-Version: 2.4
Name: dave_core
Version: 1.3.3
Summary: DAVE is a tool for automatic energy grid generation
Maintainer-email: DAVE_core Developers <tobias.banze@iee.fraunhofer.de>
Project-URL: Homepage, http://databutler.energy/
Project-URL: Documentation, https://dave-core.readthedocs.io
Project-URL: Source, https://github.com/DaveFoss/DAVE_core
Project-URL: Repository, https://github.com/DaveFoss/DAVE_core.git
Project-URL: Issues, https://github.com/DaveFoss/DAVE_core/issues
Project-URL: Download, https://pypi.org/project/dave-core/#files
Project-URL: Changelog, https://dave-core.readthedocs.io/en/latest/about/changelog.html
Keywords: power system,gas system,network,modeling,automation,grid,energy,DAVE
Classifier: Development Status :: 5 - Production/Stable
Classifier: Environment :: Console
Classifier: Intended Audience :: Developers
Classifier: Intended Audience :: Education
Classifier: Intended Audience :: Science/Research
Classifier: Natural Language :: English
Classifier: Operating System :: OS Independent
Classifier: Programming Language :: Python
Classifier: Programming Language :: Python :: 3
Classifier: Programming Language :: Python :: 3.11
Classifier: Programming Language :: Python :: 3.12
Classifier: Programming Language :: Python :: 3.13
Requires-Python: >=3.11
License-File: LICENSE
License-File: AUTHORS.rst
Requires-Dist: pandas>=2.3
Requires-Dist: Shapely>=2.1
Requires-Dist: geopandas>=1.1
Requires-Dist: matplotlib>=3.10
Requires-Dist: geopy>=2.4
Requires-Dist: fiona>=1.10
Requires-Dist: networkx>=3.5
Requires-Dist: contextily>=1.6
Requires-Dist: pytest>=8.4
Requires-Dist: pytest-cov>=6.2
Requires-Dist: pytest-xdist>=3.8
Requires-Dist: xmlschema>=4.1
Requires-Dist: lxml>=6.0
Requires-Dist: tables>=3.10
Requires-Dist: tqdm>=4.67
Requires-Dist: pandapower>=3.1
Requires-Dist: pandapipes>=0.12
Requires-Dist: defusedxml>=0.7
Requires-Dist: dask_geopandas>=0.5
Requires-Dist: scipy>=1.16
Requires-Dist: openpyxl>=3.1
Provides-Extra: docs
Requires-Dist: sphinx>=5.3.0; extra == "docs"
Requires-Dist: sphinx_rtd_theme>=1.1.1; extra == "docs"
Requires-Dist: sphinx-pyproject; extra == "docs"
Provides-Extra: dev
Requires-Dist: black; extra == "dev"
Requires-Dist: isort>=6.0; extra == "dev"
Requires-Dist: pre-commit>=4.3; extra == "dev"
Provides-Extra: all
Requires-Dist: dave_core[dev,docs]; extra == "all"
Dynamic: license-file
